{
    "navigation": {
      "home": "Home",
      "about": "About",
      "share": "Share Your Services",
      "placeholder": "Where...",
      "login": "Log in",
      "whishlists": "Wishlists",
      "help": "Help Centre",
      "logout": "Log out"
    },
    "page": {
      "home": {
        "title": "Welcome to NextJs i18n",
        "description": "Internationalization in NextJs 13 App router"
      },
      "about": {
        "title": "About Us",
        "description": "This is the about page"
      },
      "button": {
        "deploy": "Deploy now",
        "read": "Read our docs"
      }
    }
  }