{
    "navigation": {
      "home": "Laman Utama",
      "about": "Tentang Kami",
      "share": "Kongsi Perkhidmatan Anda",
      "my_service": "Perkhidmatan Saya",
      "placeholder": "Di mana...",
      "login": "Log Masuk",
      "whishlists": "Senarai Hajat",
      "help": "Pusat Bantuan",
      "logout": "Log Keluar"
    },
    "bottom_navigation": {
      "explore": "Teroka",
      "whishlists": "Senarai Hajat",
      "profile": "Profil",
      "login": "Log Masuk",
      "drawerTitle": "Pilih bahasa",
      "logout": "Log Keluar",
      "help": "Lawati Pusat Bantuan",
      "share": "Kongsi Perkhidmatan Anda",
      "my_service": "Perkhidmatan Saya",
      "shareContent": "Iklankan Perkhidmatan & Jana Pendapatan Tambahan dengan Mudah"
    },
    "service_type": {
      "home_cleaning": "Pembersihan Rumah",
      "aircon_servicing": "Pembaikan & Penyelenggaraan Penyaman Udara",
      "move_in_out_cleaning": "Pembersihan Masuk/Keluar Rumah",
      "sofa_cleaning": "Pembersihan Sofa",
      "mattress_cleaning": "Pembersihan Tilam",
      "curtain_cleaning": "Pembersihan Langsir",
      "car_washing": "Cuci Kereta",
      "disinfection_service": "Perkhidmatan Disinfeksi",
      "landscaping_service": "Perkhidmatan Landskap",
      "handyman_services": "Perkhidmatan Tukang",
      "painting_services": "Perkhidmatan Mengecat",
      "moving_service": "Perkhidmatan Pindah",
      "flooring_services": "Perkhidmatan Lantai",
      "pest_control": "Kawalan Serangga",
      "elderly_care": "Penjagaan Warga Emas",
      "child_care": "Penjagaan Kanak-kanak",
      "full_time_maid": "Pembantu Rumah Sepenuh Masa"
    },
    "overview": {
      "main": "Mudah untuk bermula di Allcareok",
      "title_1": "Beritahu kami tentang perkhidmatan anda",
      "content_1": "Berikan maklumat asas, seperti jenis perkhidmatan yang ditawarkan dan kawasan perkhidmatan yang diliputi.",
      "title_2": "Jadikan ia menonjol",
      "content_2": "Muat naik sekurang-kurangnya satu foto, bersama tajuk dan keterangan—kami akan bantu anda dengan selebihnya.",
      "title_3": "Lengkapkan dan siarkan",
      "content_3": "Sahkan beberapa butiran, kemudian kongsi iklan perkhidmatan anda dengan dunia.",
      "exit": "Keluar",
      "get_started": "Mula Sekarang"
    },
    "listing_editor_card": {
      "listing": "Editor Iklan",
      "photo_upload": "Muat Naik Foto",
      "title": "Tajuk",
      "service": "Jenis Perkhidmatan",
      "area": "Kawasan Perkhidmatan",
      "contact": "Maklumat Hubungan & Pautan Sosial",
      "description": "Penerangan",
      "location": "Lokasi",
      "delete": "Padam Perkhidmatan",
      "your_listing": "Iklan Anda",
      "photo_upload_description": "Muat naik poster perkhidmatan anda dengan maklumat hubungan, butiran perkhidmatan, dan kawasan liputan. Sertakan gambar kes sebenar untuk membantu pelanggan.",
      "add_photo": "Tambah Foto",
      "handyman": "Tukang",
      "cleaning": "Pembersihan",
      "childcare": "Penjagaan Kanak-kanak",
      "hourly_maid": "Pembantu Rumah Mengikut Jam",
      "plumber": "Tukang Paip",
      "no_items_selected": "Tiada item dipilih",
      "items_selected": "item dipilih",
      "drag": "Seret dan lepaskan",
      "browse": "atau cari foto",
      "browseBtn": "Cari",
      "done": "Selesai",
      "upload": "Muat Naik",
      "cancel": "Batal",
      "delete_left_content": "Setelah anda memadam perkhidmatan, tiada cara untuk mengembalikannya. Pastikan keputusan anda muktamad.",
      "delete_right_content": "Perkhidmatan, bersama gambar dan semua maklumat yang berkaitan, akan dipadam secara kekal. Tindakan ini tidak boleh diubah.",
      "delete_btn": "Padam Perkhidmatan",
      "delete_modal_title": "Padam perkhidmatan ini secara kekal?",
      "delete_modal_btn": "Padam",
      "make_cover": "Jadikan Foto Penutup",
      "boosts_card_title": "Tingkatkan Perkhidmatan Anda",
      "boosts_card_content": "Cari pelan terbaik untuk meningkatkan perkhidmatan anda.",
      "title_right_label": "Tajuk",
      "character_available": "aksara tersedia",
      "over_limit": "aksara melebihi had",
      "title_save": "Simpan",
      "area_button": "Kawasan",
      "area_content": "Sila nyatakan kawasan perkhidmatan anda dengan jelas, kerana pelanggan sering mencari perkhidmatan berdasarkan lokasi.",
      "map": "Peta",
      "select_country": "Pilih Negara",
      "state": "Negeri / Wilayah Persekutuan",
      "city": "Bandar / Majlis Perbandaran",
      "town": "Pekan / Kawasan Kejiranan",
      "add_service_area": "Tambah Kawasan Perkhidmatan",
      "add_detail": "Tambah Butiran"
    }
  }